setup.py
disclose/__init__.py
disclose/patch_json.py
disclose.egg-info/PKG-INFO
disclose.egg-info/SOURCES.txt
disclose.egg-info/dependency_links.txt
disclose.egg-info/top_level.txt