Metadata-Version: 1.1
Name: disclose
Version: 0.2.5
Summary: A utility for test verifications
Home-page: https://github.com/silasray/disclose
Author: Silas Ray
Author-email: silas.ray@nytimes.com
License: Apache2.0
Platform: UNKNOWN
Classifier: Development Status :: 4 - Beta
Classifier: Intended Audience :: Developers
Classifier: Intended Audience :: Information Technology
Classifier: Topic :: Software Development :: Quality Assurance
Classifier: Topic :: Software Development :: Testing
